rtl/decode_unit.sv
//
// decode_unit.sv
// NeoCore 16x32 CPU - Instruction Decode Unit
//
// Decodes variable-length instructions and extracts:
// - Opcode and specifier
// - Source and destination register addresses
// - Immediate values
// - Memory addresses
// - Branch targets
//
// Big-Endian Instruction Format:
//   inst_data[71:64]   = Byte 0 (Specifier)
//   inst_data[63:56]   = Byte 1 (Opcode)
//   inst_data[55:48]   = Byte 2 (rd or first operand byte)
//   inst_data[47:40]   = Byte 3
//   ...
//   inst_data[7:0]     = Byte 8 (last byte for longest instructions)
//

module decode_unit
  import neocore_pkg::*;
(
  input  logic         clk,
  input  logic         rst,
  
  // Input instruction (big-endian)
  input  logic [71:0]  inst_data,    // Instruction data (up to 9 bytes)
  input  logic [3:0]   inst_len,     // Instruction length
  input  logic [31:0]  pc,           // Current PC
  input  logic         valid_in,     // Instruction valid
  
  // Decoded outputs
  output logic         valid_out,
  output opcode_e      opcode,
  output logic [7:0]   specifier,
  output itype_e       itype,
  output alu_op_e      alu_op,
  
  // Register addresses
  output logic [3:0]   rs1_addr,
  output logic [3:0]   rs2_addr,
  output logic [3:0]   rd_addr,
  output logic [3:0]   rd2_addr,
  
  // Immediate/address values
  output logic [31:0]  immediate,
  output logic [31:0]  mem_addr,
  output logic [31:0]  branch_target,
  
  // Control signals
  output logic         rd_we,        // Destination register write enable
  output logic         rd2_we,       // Second destination write enable
  output logic         mem_read,
  output logic         mem_write,
  output mem_size_e    mem_size,
  output logic         is_branch,
  output logic         is_jsr,
  output logic         is_rts,
  output logic         is_halt
);

  // ============================================================================
  // Instruction Field Extraction (Big-Endian)
  // ============================================================================
  
  // Extract individual bytes from instruction data
  // Big-endian: MSB bytes at higher bit positions
  logic [7:0] byte0, byte1, byte2, byte3, byte4, byte5, byte6, byte7, byte8;
  
  always_comb begin
    byte0  = inst_data[71:64];   // Specifier
    byte1  = inst_data[63:56];   // Opcode
    byte2  = inst_data[55:48];   // rd (for most instructions)
    byte3  = inst_data[47:40];   // rn or immediate byte
    byte4  = inst_data[39:32];   // immediate byte or rn1
    byte5  = inst_data[31:24];   // address/immediate byte
    byte6  = inst_data[23:16];   // address/immediate byte
    byte7  = inst_data[15:8];    // address/immediate byte
    byte8  = inst_data[7:0];     // address/immediate byte (for longest instructions)
  end
  
  // ============================================================================
  // Opcode and Type Decoding
  // ============================================================================
  
  opcode_e opcode_int;
  
  always_comb begin
    opcode_int = opcode_e'(byte1);
    opcode = opcode_int;
    specifier = byte0;
    itype = get_itype(opcode_int);
    alu_op = opcode_to_alu_op(opcode_int);
    valid_out = valid_in;
  end
  
  // ============================================================================
  // Register Address Decoding
  // ============================================================================
  
  always_comb begin
    // Default values
    rs1_addr = 4'h0;
    rs2_addr = 4'h0;
    rd_addr = 4'h0;
    rd2_addr = 4'h0;
    
    case (opcode_int)
      OP_ADD, OP_SUB, OP_MUL, OP_AND, OP_OR, OP_XOR, OP_LSH, OP_RSH: begin
        // ALU instructions
        rd_addr = byte2[3:0];
        case (specifier)
          8'h00: begin  // rd, #immediate
            rs1_addr = byte2[3:0];  // rd is also source
            rs2_addr = 4'h0;
          end
          8'h01: begin  // rd, rn
            rs1_addr = byte3[3:0];  // rn
            rs2_addr = byte2[3:0];  // rd
          end
          8'h02: begin  // rd, [address]
            rs1_addr = 4'h0;  // Will load from memory
            rs2_addr = byte2[3:0];  // rd
          end
          default: begin
            rs1_addr = 4'h0;
            rs2_addr = 4'h0;
          end
        endcase
      end
      
      OP_MOV: begin
        // MOV instructions - many variants
        rd_addr = byte2[3:0];
        case (specifier)
          8'h00: begin  // mov rd, #immediate
            rs1_addr = 4'h0;
            rs2_addr = 4'h0;
          end
          8'h01: begin  // mov rd, rn, label
            rs1_addr = byte3[3:0];  // rn
            rs2_addr = 4'h0;
          end
          8'h02: begin  // mov rd, rn
            rs1_addr = byte3[3:0];  // rn
            rs2_addr = 4'h0;
          end
          8'h03, 8'h04, 8'h05: begin  // mov rd.L/H, [addr] or mov rd, [addr]
            rs1_addr = 4'h0;  // Load from memory
            rs2_addr = 4'h0;
          end
          8'h06: begin  // mov rd, rn1, [addr]
            rs1_addr = byte3[3:0];  // rn1
            rd2_addr = byte3[3:0];  // rn1 also destination
          end
          8'h07, 8'h08, 8'h09: begin  // mov [addr], rd.L/H or rd
            rs1_addr = byte2[3:0];  // rd to store
            rs2_addr = 4'h0;
            rd_addr = 4'h0;  // No destination (store only)
          end
          8'h0A: begin  // mov [addr], rd, rn1
            rs1_addr = byte2[3:0];  // rd
            rs2_addr = byte3[3:0];  // rn1
            rd_addr = 4'h0;
          end
          8'h0B, 8'h0C, 8'h0D: begin  // mov rd.L/H, [rn + offset] or rd
            rs1_addr = byte3[3:0];  // rn (base address)
            rs2_addr = 4'h0;
          end
          8'h0E: begin  // mov rd, rd1, [rn + offset]
            rs1_addr = byte4[3:0];  // rn
            rd2_addr = byte3[3:0];  // rd1
          end
          8'h0F, 8'h10, 8'h11: begin  // mov [rn + offset], rd.L/H or rd
            rs1_addr = byte2[3:0];  // rd (data to store)
            rs2_addr = byte3[3:0];  // rn (base)
            rd_addr = 4'h0;
          end
          8'h12: begin  // mov [rn + offset], rd, rn1
            rs1_addr = byte2[3:0];  // rd
            rs2_addr = byte4[3:0];  // rn (base)
            rd_addr = 4'h0;
          end
          default: begin
            rs1_addr = 4'h0;
            rs2_addr = 4'h0;
          end
        endcase
      end
      
      OP_BE, OP_BNE, OP_BLT, OP_BGT: begin
        // Conditional branches with two operands
        rs1_addr = byte2[3:0];  // rd
        rs2_addr = byte3[3:0];  // rn
        rd_addr = 4'h0;  // No write
      end
      
      OP_UMULL, OP_SMULL: begin
        // Multiply long: rd, rn, rn1
        rd_addr = byte2[3:0];   // rd (low result)
        rd2_addr = byte3[3:0];  // rn (high result)
        rs1_addr = byte3[3:0];  // rn (operand 1)
        rs2_addr = byte4[3:0];  // rn1 (operand 2)
      end
      
      OP_PSH: begin
        // Push: rd
        rs1_addr = byte2[3:0];  // rd (value to push)
        rd_addr = 4'h0;
      end
      
      OP_POP: begin
        // Pop: rd
        rd_addr = byte2[3:0];  // rd (destination)
        rs1_addr = 4'h0;
      end
      
      default: begin
        // NOP, HLT, B, JSR, RTS, WFI, BRO, ENI, DSI
        rs1_addr = 4'h0;
        rs2_addr = 4'h0;
        rd_addr = 4'h0;
        rd2_addr = 4'h0;
      end
    endcase
  end
  
  // ============================================================================
  // Immediate and Address Extraction (Big-Endian)
  // ============================================================================
  
  always_comb begin
    immediate = 32'h0;
    mem_addr = 32'h0;
    branch_target = 32'h0;
    
    case (opcode_int)
      OP_ADD, OP_SUB, OP_MUL, OP_AND, OP_OR, OP_XOR, OP_LSH, OP_RSH: begin
        case (specifier)
          8'h00: begin  // Immediate (16-bit, big-endian)
            immediate = {16'h0, byte3, byte4};
          end
          8'h02: begin  // Memory address (32-bit, big-endian)
            mem_addr = {byte3, byte4, byte5, byte6};
          end
          default: immediate = 32'h0;
        endcase
      end
      
      OP_MOV: begin
        case (specifier)
          8'h00: begin  // mov rd, #immediate (16-bit)
            immediate = {16'h0, byte3, byte4};
          end
          8'h01: begin  // mov rd, rn, label (32-bit address)
            branch_target = {byte4, byte5, byte6, byte7};
          end
          8'h03, 8'h04, 8'h05, 8'h07, 8'h08, 8'h09: begin  // [normAddressing]
            mem_addr = {byte3, byte4, byte5, byte6};
          end
          8'h06, 8'h0A: begin  // rd, rn1, [normAddressing]
            mem_addr = {byte4, byte5, byte6, byte7};
          end
          8'h0B, 8'h0C, 8'h0D, 8'h0F, 8'h10, 8'h11: begin  // [rn + offset]
            immediate = {byte4, byte5, byte6, byte7};  // offset
          end
          8'h0E, 8'h12: begin  // rd, rd1, [rn + offset] or [rn + offset], rd, rn1
            immediate = {byte5, byte6, byte7, byte8};  // offset
          end
          default: immediate = 32'h0;
        endcase
      end
      
      OP_B, OP_JSR: begin
        // Unconditional branch/jump (32-bit address)
        branch_target = {byte2, byte3, byte4, byte5};
      end
      
      OP_BE, OP_BNE, OP_BLT, OP_BGT, OP_BRO: begin
        // Conditional branch (32-bit address)
        if (opcode_int == OP_BRO) begin
          // BRO has no operands, just label
          branch_target = {byte2, byte3, byte4, byte5};
        end else begin
          // Other branches have rd, rn, label
          branch_target = {byte4, byte5, byte6, byte7};
        end
      end
      
      default: begin
        immediate = 32'h0;
        mem_addr = 32'h0;
        branch_target = 32'h0;
      end
    endcase
  end
  
  // ============================================================================
  // Control Signal Generation
  // ============================================================================
  
  always_comb begin
    // Default values
    rd_we = 1'b0;
    rd2_we = 1'b0;
    mem_read = 1'b0;
    mem_write = 1'b0;
    mem_size = MEM_HALF;
    is_branch = 1'b0;
    is_jsr = 1'b0;
    is_rts = 1'b0;
    is_halt = 1'b0;
    
    if (valid_in) begin
      case (opcode_int)
        OP_ADD, OP_SUB, OP_MUL, OP_AND, OP_OR, OP_XOR, OP_LSH, OP_RSH: begin
          // ALU operations
          rd_we = 1'b1;
          if (specifier == 8'h02) begin
            // Load operand from memory
            mem_read = 1'b1;
            mem_size = MEM_HALF;
          end
        end
        
        OP_MOV: begin
          case (specifier)
            8'h00, 8'h01, 8'h02: begin  // Register moves
              rd_we = 1'b1;
            end
            8'h03: begin  // mov rd.L, [addr] - byte load
              rd_we = 1'b1;
              mem_read = 1'b1;
              mem_size = MEM_BYTE;
            end
            8'h04: begin  // mov rd.H, [addr] - byte load to high
              rd_we = 1'b1;
              mem_read = 1'b1;
              mem_size = MEM_BYTE;
            end
            8'h05, 8'h0B, 8'h0C, 8'h0D: begin  // mov rd, [addr] - halfword load
              rd_we = 1'b1;
              mem_read = 1'b1;
              mem_size = MEM_HALF;
            end
            8'h06, 8'h0E: begin  // Two-register load
              rd_we = 1'b1;
              rd2_we = 1'b1;
              mem_read = 1'b1;
              mem_size = MEM_WORD;
            end
            8'h07: begin  // mov [addr], rd.L - byte store
              mem_write = 1'b1;
              mem_size = MEM_BYTE;
            end
            8'h08: begin  // mov [addr], rd.H - byte store from high
              mem_write = 1'b1;
              mem_size = MEM_BYTE;
            end
            8'h09, 8'h0F, 8'h10, 8'h11: begin  // mov [addr], rd - halfword store
              mem_write = 1'b1;
              mem_size = MEM_HALF;
            end
            8'h0A, 8'h12: begin  // Two-register store
              mem_write = 1'b1;
              mem_size = MEM_WORD;
            end
            default: begin
              // Unknown specifier
            end
          endcase
        end
        
        OP_B, OP_BE, OP_BNE, OP_BLT, OP_BGT, OP_BRO: begin
          is_branch = 1'b1;
        end
        
        OP_JSR: begin
          is_jsr = 1'b1;
          is_branch = 1'b1;
        end
        
        OP_RTS: begin
          is_rts = 1'b1;
          is_branch = 1'b1;
        end
        
        OP_HLT: begin
          is_halt = 1'b1;
        end
        
        OP_UMULL, OP_SMULL: begin
          // Multiply long - writes two registers
          rd_we = 1'b1;
          rd2_we = 1'b1;
        end
        
        OP_PSH: begin
          // Push to stack - memory write
          mem_write = 1'b1;
          mem_size = MEM_HALF;
        end
        
        OP_POP: begin
          // Pop from stack - memory read
          rd_we = 1'b1;
          mem_read = 1'b1;
          mem_size = MEM_HALF;
        end
        
        OP_WFI, OP_ENI, OP_DSI, OP_NOP: begin
          // Control instructions - no register/memory access
          // WFI, ENI, DSI would be handled by interrupt controller (not implemented)
        end
        
        default: begin
          // Unknown opcode
        end
      endcase
    end
  end

endmodule : decode_unit

tb/decode_unit_tb.sv
//
// decode_unit_tb.sv
// Testbench for Decode Unit module
//
// Tests instruction decoding for key instruction types.
// Updated for big-endian, 72-bit (9-byte) instruction format.
//

`timescale 1ns/1ps

module decode_unit_tb;
  import neocore_pkg::*;

  // Testbench signals
  logic        clk;
  logic        rst;
  logic [71:0] inst_data;  // 9 bytes max (padded to 72 bits)
  logic [3:0]  inst_len;
  logic [31:0] pc;
  logic        valid_in;
  logic        valid_out;
  opcode_e     opcode;
  logic [7:0]  specifier;
  itype_e      itype;
  alu_op_e     alu_op;
  logic [3:0]  rs1_addr;
  logic [3:0]  rs2_addr;
  logic [3:0]  rd_addr;
  logic [3:0]  rd2_addr;
  logic [31:0] immediate;
  logic [31:0] mem_addr;
  logic [31:0] branch_target;
  logic        rd_we;
  logic        rd2_we;
  logic        mem_read;
  logic        mem_write;
  mem_size_e   mem_size;
  logic        is_branch;
  logic        is_jsr;
  logic        is_rts;
  logic        is_halt;
  
  // Instantiate decode unit
  decode_unit dut (
    .clk(clk),
    .rst(rst),
    .inst_data(inst_data),
    .inst_len(inst_len),
    .pc(pc),
    .valid_in(valid_in),
    .valid_out(valid_out),
    .opcode(opcode),
    .specifier(specifier),
    .itype(itype),
    .alu_op(alu_op),
    .rs1_addr(rs1_addr),
    .rs2_addr(rs2_addr),
    .rd_addr(rd_addr),
    .rd2_addr(rd2_addr),
    .immediate(immediate),
    .mem_addr(mem_addr),
    .branch_target(branch_target),
    .rd_we(rd_we),
    .rd2_we(rd2_we),
    .mem_read(mem_read),
    .mem_write(mem_write),
    .mem_size(mem_size),
    .is_branch(is_branch),
    .is_jsr(is_jsr),
    .is_rts(is_rts),
    .is_halt(is_halt)
  );
  
  // Clock generation
  initial begin
    clk = 0;
    forever #5 clk = ~clk;
  end
  
  // VCD dump for waveform viewing
  initial begin
    $dumpfile("decode_unit_tb.vcd");
    $dumpvars(0, decode_unit_tb);
  end
  
  // Test stimulus
  initial begin
    $display("========================================");
    $display("Decode Unit Testbench");
    $display("========================================");
    
    // Initialize
    rst = 1;
    inst_data = 72'h0;
    inst_len = 4'd0;
    pc = 32'h0000_0000;
    valid_in = 1'b0;
    @(posedge clk);
    rst = 0;
    @(posedge clk);
    
    // Test 1: NOP instruction
    $display("\nTest 1: NOP");
    // Big-Endian Format: byte0=spec, byte1=op
    // [sp(8)] [opcode(8)] = [00] [00]
    // Bit positions: [71:64][63:56]
    inst_data = 72'h00_00_00_00_00_00_00_00_00;
    inst_len = 4'd2;
    pc = 32'h0000_0100;
    valid_in = 1'b1;
    @(posedge clk);
    #1;
    assert(opcode == OP_NOP) else $error("Opcode mismatch");
    assert(itype == ITYPE_CTRL) else $error("Type mismatch");
    assert(valid_out == 1'b1) else $error("Valid mismatch");
    $display("  PASS: NOP decoded correctly");
    
    // Test 2: ADD immediate (rd = rd + imm)
    $display("\nTest 2: ADD R1, #0x1234");
    // Big-Endian: [sp][op][rd][imm_hi][imm_lo] = [00][01][01][12][34]
    // Bits: [71:64][63:56][55:48][47:40][39:32]
    inst_data = 72'h00_01_01_12_34_00_00_00_00;
    inst_len = 4'd5;
    valid_in = 1'b1;
    @(posedge clk);
    #1;
    assert(opcode == OP_ADD) else $error("Opcode mismatch");
    assert(specifier == 8'h00) else $error("Specifier mismatch");
    assert(itype == ITYPE_ALU) else $error("Type mismatch");
    assert(alu_op == ALU_ADD) else $error("ALU op mismatch");
    assert(rd_addr == 4'd1) else $error("rd mismatch");
    assert(rs1_addr == 4'd1) else $error("rs1 mismatch (should be rd)");
    assert(immediate == 32'h0000_1234) else $error("Immediate mismatch: got %h", immediate);
    assert(rd_we == 1'b1) else $error("rd_we should be 1");
    $display("  PASS: ADD immediate decoded");
    
    // Test 3: ADD register (rd = rd + rn)
    $display("\nTest 3: ADD R2, R3");
    // Big-Endian: [sp][op][rd][rn] = [01][01][02][03]
    inst_data = 72'h01_01_02_03_00_00_00_00_00;
    inst_len = 4'd4;
    @(posedge clk);
    #1;
    assert(opcode == OP_ADD) else $error("Opcode mismatch");
    assert(specifier == 8'h01) else $error("Specifier mismatch");
    assert(rd_addr == 4'd2) else $error("rd mismatch");
    assert(rs1_addr == 4'd3) else $error("rs1 (rn) mismatch");
    assert(rs2_addr == 4'd2) else $error("rs2 (rd) mismatch");
    $display("  PASS: ADD register decoded");
    
    // Test 4: MOV immediate 16-bit
    $display("\nTest 4: MOV R5, #0xABCD");
    // Big-Endian: [sp][op][rd][imm_hi][imm_lo] = [00][09][05][AB][CD]
    inst_data = 72'h00_09_05_AB_CD_00_00_00_00;
    inst_len = 4'd5;
    @(posedge clk);
    #1;
    assert(opcode == OP_MOV) else $error("Opcode mismatch");
    assert(specifier == 8'h00) else $error("Specifier mismatch");
    assert(itype == ITYPE_MOV) else $error("Type mismatch");
    assert(rd_addr == 4'd5) else $error("rd mismatch");
    assert(immediate == 32'h0000_ABCD) else $error("Immediate mismatch");
    assert(rd_we == 1'b1) else $error("rd_we should be 1");
    $display("  PASS: MOV immediate decoded");
    
    // Test 5: Unconditional branch
    $display("\nTest 5: B 0x12345678");
    // Big-Endian: [sp][op][addr3][addr2][addr1][addr0] = [00][0A][12][34][56][78]
    inst_data = 72'h00_0A_12_34_56_78_00_00_00;
    inst_len = 4'd6;
    @(posedge clk);
    #1;
    assert(opcode == OP_B) else $error("Opcode mismatch");
    assert(itype == ITYPE_BRANCH) else $error("Type mismatch");
    assert(is_branch == 1'b1) else $error("is_branch should be 1");
    assert(branch_target == 32'h1234_5678) else $error("Branch target mismatch: got %h", branch_target);
    $display("  PASS: B decoded with target 0x%08h", branch_target);
    
    // Test 6: BNE (branch if not equal)
    $display("\nTest 6: BNE R1, R2, 0xABCD0000");
    // Big-Endian: [sp][op][rd][rn][addr3][addr2][addr1][addr0] = [00][0C][01][02][AB][CD][00][00]
    inst_data = 72'h00_0C_01_02_AB_CD_00_00_00;
    inst_len = 4'd8;
    @(posedge clk);
    #1;
    assert(opcode == OP_BNE) else $error("Opcode mismatch");
    assert(is_branch == 1'b1) else $error("is_branch should be 1");
    assert(rs1_addr == 4'd1) else $error("rs1 mismatch");
    assert(rs2_addr == 4'd2) else $error("rs2 mismatch");
    assert(branch_target == 32'hABCD_0000) else $error("Branch target mismatch");
    $display("  PASS: BNE decoded");
    
    // Test 7: HLT instruction
    $display("\nTest 7: HLT");
    // Big-Endian: [sp][op] = [00][12]
    inst_data = 72'h00_12_00_00_00_00_00_00_00;
    inst_len = 4'd2;
    @(posedge clk);
    #1;
    assert(opcode == OP_HLT) else $error("Opcode mismatch");
    assert(is_halt == 1'b1) else $error("is_halt should be 1");
    $display("  PASS: HLT decoded");
    
    // Test 8: UMULL (unsigned multiply long)
    $display("\nTest 8: UMULL R1, R2, R3");
    // Big-Endian: [sp][op][rd][rn][rn1] = [00][10][01][02][03]
    inst_data = 72'h00_10_01_02_03_00_00_00_00;
    inst_len = 4'd5;
    @(posedge clk);
    #1;
    assert(opcode == OP_UMULL) else $error("Opcode mismatch");
    assert(itype == ITYPE_MUL) else $error("Type mismatch");
    assert(rd_addr == 4'd1) else $error("rd mismatch");
    assert(rd2_addr == 4'd2) else $error("rd2 mismatch");
    assert(rs2_addr == 4'd3) else $error("rs2 (rn1) mismatch");
    assert(rd_we == 1'b1) else $error("rd_we should be 1");
    assert(rd2_we == 1'b1) else $error("rd2_we should be 1");
    $display("  PASS: UMULL decoded");
    
    $display("\n========================================");
    $display("Decode Unit Testbench PASSED");
    $display("========================================\n");
    
    $finish;
  end

endmodule

decode_unit_tb.vcd
$date
	Fri Nov 28 22:49:58 2025
$end
$version
	Icarus Verilog
$end
$timescale
	1ps
$end
$scope module decode_unit_tb $end
$var wire 1 ! valid_out $end
$var wire 8 " specifier [7:0] $end
$var wire 4 # rs2_addr [3:0] $end
$var wire 4 $ rs1_addr [3:0] $end
$var wire 1 % rd_we $end
$var wire 4 & rd_addr [3:0] $end
$var wire 1 ' rd2_we $end
$var wire 4 ( rd2_addr [3:0] $end
$var wire 8 ) opcode [7:0] $end
$var wire 1 * mem_write $end
$var wire 2 + mem_size [1:0] $end
$var wire 1 , mem_read $end
$var wire 32 - mem_addr [31:0] $end
$var wire 4 . itype [3:0] $end
$var wire 1 / is_rts $end
$var wire 1 0 is_jsr $end
$var wire 1 1 is_halt $end
$var wire 1 2 is_branch $end
$var wire 32 3 immediate [31:0] $end
$var wire 32 4 branch_target [31:0] $end
$var wire 4 5 alu_op [3:0] $end
$var reg 1 6 clk $end
$var reg 72 7 inst_data [71:0] $end
$var reg 4 8 inst_len [3:0] $end
$var reg 32 9 pc [31:0] $end
$var reg 1 : rst $end
$var reg 1 ; valid_in $end
$scope module dut $end
$var wire 1 6 clk $end
$var wire 72 < inst_data [71:0] $end
$var wire 4 = inst_len [3:0] $end
$var wire 32 > pc [31:0] $end
$var wire 1 : rst $end
$var wire 1 ; valid_in $end
$var reg 4 ? alu_op [3:0] $end
$var reg 32 @ branch_target [31:0] $end
$var reg 8 A byte0 [7:0] $end
$var reg 8 B byte1 [7:0] $end
$var reg 8 C byte2 [7:0] $end
$var reg 8 D byte3 [7:0] $end
$var reg 8 E byte4 [7:0] $end
$var reg 8 F byte5 [7:0] $end
$var reg 8 G byte6 [7:0] $end
$var reg 8 H byte7 [7:0] $end
$var reg 8 I byte8 [7:0] $end
$var reg 32 J immediate [31:0] $end
$var reg 1 2 is_branch $end
$var reg 1 1 is_halt $end
$var reg 1 0 is_jsr $end
$var reg 1 / is_rts $end
$var reg 4 K itype [3:0] $end
$var reg 32 L mem_addr [31:0] $end
$var reg 1 , mem_read $end
$var reg 2 M mem_size [1:0] $end
$var reg 1 * mem_write $end
$var reg 8 N opcode [7:0] $end
$var reg 8 O opcode_int [7:0] $end
$var reg 4 P rd2_addr [3:0] $end
$var reg 1 ' rd2_we $end
$var reg 4 Q rd_addr [3:0] $end
$var reg 1 % rd_we $end
$var reg 4 R rs1_addr [3:0] $end
$var reg 4 S rs2_addr [3:0] $end
$var reg 8 T specifier [7:0] $end
$var reg 1 ! valid_out $end
$upscope $end
$upscope $end
$enddefinitions $end
$comment Show the parameter values. $end
$dumpall
$end
#0
$dumpvars
b0 T
b0 S
b0 R
b0 Q
b0 P
b0 O
b0 N
b1 M
b0 L
b110 K
b0 J
b0 I
b0 H
b0 G
b0 F
b0 E
b0 D
b0 C
b0 B
b0 A
b0 @
b1111 ?
b0 >
b0 =
b0 <
0;
1:
b0 9
b0 8
b0 7
06
b1111 5
b0 4
b0 3
02
01
00
0/
b110 .
b0 -
0,
b1 +
0*
b0 )
b0 (
0'
b0 &
0%
b0 $
b0 #
b0 "
0!
$end
#5000
0:
16
#10000
06
#15000
1!
1;
b100000000 9
b100000000 >
b10 8
b10 =
16
#20000
06
#25000
16
#26000
1%
b1001000110100 3
b1001000110100 J
b1 $
b1 R
b1 &
b1 Q
b0 5
b0 ?
b0 .
b0 K
b1 )
b1 N
b1 O
b110100 E
b10010 D
b1 C
b1 B
b101 8
b101 =
b100000001000100100011010000000000000000000000000000000000 7
b100000001000100100011010000000000000000000000000000000000 <
#30000
06
#35000
16
#36000
1%
b0 3
b0 J
b10 #
b10 S
b10 &
b10 Q
b11 $
b11 R
b1 "
b1 T
b0 E
b11 D
b10 C
b1 A
b100 8
b100 =
b10000000100000010000000110000000000000000000000000000000000000000 7
b10000000100000010000000110000000000000000000000000000000000000000 <
#40000
06
#45000
16
#46000
1%
b1010101111001101 3
b1010101111001101 J
b101 &
b101 Q
b0 #
b0 S
b0 $
b0 R
b1111 5
b1111 ?
b1 .
b1 K
b0 "
b0 T
b1001 )
b1001 N
b1001 O
b11001101 E
b10101011 D
b101 C
b1001 B
b0 A
b101 8
b101 =
b100100000101101010111100110100000000000000000000000000000000 7
b100100000101101010111100110100000000000000000000000000000000 <
#50000
06
#55000
16
#56000
12
0%
b10010001101000101011001111000 4
b10010001101000101011001111000 @
b0 3
b0 J
b0 &
b0 Q
b10 .
b10 K
b1010 )
b1010 N
b1010 O
b1111000 F
b1010110 E
b110100 D
b10010 C
b1010 B
b110 8
b110 =
b101000010010001101000101011001111000000000000000000000000000 7
b101000010010001101000101011001111000000000000000000000000000 <
#60000
06
#65000
16
#66000
12
b10101011110011010000000000000000 4
b10101011110011010000000000000000 @
b10 #
b10 S
b1 $
b1 R
b1100 )
b1100 N
b1100 O
b11001101 F
b10101011 E
b10 D
b1 C
b1100 B
b1000 8
b1000 =
b110000000001000000101010101111001101000000000000000000000000 7
b110000000001000000101010101111001101000000000000000000000000 <
#70000
06
#75000
16
#76000
11
02
b0 4
b0 @
b0 #
b0 S
b0 $
b0 R
b110 .
b110 K
b10010 )
b10010 N
b10010 O
b0 F
b0 E
b0 D
b0 C
b10010 B
b10 8
b10 =
b1001000000000000000000000000000000000000000000000000000000000 7
b1001000000000000000000000000000000000000000000000000000000000 <
#80000
06
#85000
16
#86000
1'
1%
01
b11 #
b11 S
b10 $
b10 R
b10 (
b10 P
b1 &
b1 Q
b11 .
b11 K
b10000 )
b10000 N
b10000 O
b11 E
b10 D
b1 C
b10000 B
b101 8
b101 =
b1000000000001000000100000001100000000000000000000000000000000 7
b1000000000001000000100000001100000000000000000000000000000000 <
